jupyter_whisper/__init__.py
jupyter_whisper/__version__.py
jupyter_whisper/cell_outputs copy.py
jupyter_whisper/cell_outputs.py
jupyter_whisper/config.py
jupyter_whisper/search.py
jupyter_whisper/server.py
jupyter_whisper/static/main.js
jupyter_whisper/static/voicerecorder.js
jupyter_whisper-0.3.0.dist-info/licenses/LICENSE
jupyter_whisper-0.3.0.dist-info/METADATA
jupyter_whisper-0.3.0.dist-info/WHEEL
jupyter_whisper-0.3.0.dist-info/top_level.txt
jupyter_whisper-0.3.0.dist-info/RECORD
