Metadata-Version: 2.4
Name: jupyter_whisper
Version: 0.3.0
Summary: AI-Powered Chat Interface for Jupyter Notebooks
Author-email: Maxime Rivest <mrive052@gmail.com>
License: MIT License
Project-URL: Homepage, https://github.com/MaximeRivest/jupyter_whisper
Project-URL: Bug Reports, https://github.com/MaximeRivest/jupyter_whisper/issues
Project-URL: Source, https://github.com/MaximeRivest/jupyter_whisper
Keywords: jupyter,chat,claude,ai,notebook,assistant
Classifier: Development Status :: 4 - Beta
Classifier: Intended Audience :: Science/Research
Classifier: Intended Audience :: Developers
Classifier: License :: OSI Approved :: MIT License
Classifier: Programming Language :: Python :: 3
Classifier: Programming Language :: Python :: 3.7
Classifier: Programming Language :: Python :: 3.8
Classifier: Programming Language :: Python :: 3.9
Classifier: Programming Language :: Python :: 3.10
Classifier: Programming Language :: Python :: 3.11
Classifier: Programming Language :: Python :: 3.12
Classifier: Framework :: Jupyter
Classifier: Framework :: Jupyter :: JupyterLab
Classifier: Topic :: Scientific/Engineering :: Artificial Intelligence
Requires-Python: >=3.7
License-File: LICENSE
Requires-Dist: jupyterlab>=4.2.0
Requires-Dist: ipylab>=1.0.0
Requires-Dist: jupyter-server>=2.14.0
Requires-Dist: anthropic>=0.37.0
Requires-Dist: openai>=1.51.0
Requires-Dist: claudette
Requires-Dist: fastapi>=0.115.0
Requires-Dist: uvicorn>=0.31.0
Requires-Dist: nest-asyncio>=1.6.0
Requires-Dist: pydantic>=2.9.0
Requires-Dist: pydantic-settings>=2.5.2
Requires-Dist: requests>=2.32.0
Requires-Dist: python-multipart>=0.0.5
Requires-Dist: ipywidgets>=8.1.0
Dynamic: license-file
